Compiled from "IChunkAccessorSync.java"
public interface com.hypixel.hytale.server.core.universe.world.accessor.IChunkAccessorSync<WorldChunk extends com.hypixel.hytale.server.core.universe.world.accessor.BlockAccessor> {
  public abstract WorldChunk getChunkIfInMemory(long);

  public abstract WorldChunk loadChunkIfInMemory(long);

  public abstract WorldChunk getChunkIfLoaded(long);

  public abstract WorldChunk getChunkIfNonTicking(long);

  public abstract WorldChunk getChunk(long);

  public abstract WorldChunk getNonTickingChunk(long);

  public default int getBlock(org.joml.Vector3i);
    Code:
         0: aload_0
         1: aload_1
         2: invokevirtual #1                  // Method org/joml/Vector3i.x:()I
         5: aload_1
         6: invokevirtual #7                  // Method org/joml/Vector3i.y:()I
         9: aload_1
        10: invokevirtual #10                 // Method org/joml/Vector3i.z:()I
        13: invokeinterface #13,  4           // InterfaceMethod getBlock:(III)I
        18: ireturn

  public default int getBlock(int, int, int);
    Code:
         0: iload_1
         1: iload_3
         2: invokestatic  #19                 // Method com/hypixel/hytale/math/util/ChunkUtil.indexChunkFromBlock:(II)J
         5: lstore        4
         7: aload_0
         8: lload         4
        10: invokeinterface #25,  3           // InterfaceMethod getChunk:(J)Lcom/hypixel/hytale/server/core/universe/world/accessor/BlockAccessor;
        15: astore        6
        17: aload         6
        19: ifnonnull     24
        22: iconst_0
        23: ireturn
        24: aload         6
        26: iload_1
        27: iload_2
        28: iload_3
        29: invokeinterface #31,  4           // InterfaceMethod com/hypixel/hytale/server/core/universe/world/accessor/BlockAccessor.getBlock:(III)I
        34: ireturn

  public default com.hypixel.hytale.server.core.asset.type.blocktype.config.BlockType getBlockType(org.joml.Vector3i);
    Code:
         0: aload_0
         1: aload_1
         2: invokevirtual #1                  // Method org/joml/Vector3i.x:()I
         5: aload_1
         6: invokevirtual #7                  // Method org/joml/Vector3i.y:()I
         9: aload_1
        10: invokevirtual #10                 // Method org/joml/Vector3i.z:()I
        13: invokeinterface #34,  4           // InterfaceMethod getBlockType:(III)Lcom/hypixel/hytale/server/core/asset/type/blocktype/config/BlockType;
        18: areturn

  public default com.hypixel.hytale.server.core.asset.type.blocktype.config.BlockType getBlockType(int, int, int);
    Code:
         0: iload_1
         1: iload_3
         2: invokestatic  #19                 // Method com/hypixel/hytale/math/util/ChunkUtil.indexChunkFromBlock:(II)J
         5: lstore        4
         7: aload_0
         8: lload         4
        10: invokeinterface #25,  3           // InterfaceMethod getChunk:(J)Lcom/hypixel/hytale/server/core/universe/world/accessor/BlockAccessor;
        15: astore        6
        17: aload         6
        19: ifnonnull     24
        22: aconst_null
        23: areturn
        24: aload         6
        26: iload_1
        27: iload_2
        28: iload_3
        29: invokeinterface #31,  4           // InterfaceMethod com/hypixel/hytale/server/core/universe/world/accessor/BlockAccessor.getBlock:(III)I
        34: istore        7
        36: invokestatic  #38                 // Method com/hypixel/hytale/server/core/asset/type/blocktype/config/BlockType.getAssetMap:()Lcom/hypixel/hytale/assetstore/map/BlockTypeAssetMap;
        39: iload         7
        41: invokevirtual #42                 // Method com/hypixel/hytale/assetstore/map/BlockTypeAssetMap.getAsset:(I)Lcom/hypixel/hytale/assetstore/map/JsonAssetWithMap;
        44: checkcast     #29                 // class com/hypixel/hytale/server/core/asset/type/blocktype/config/BlockType
        47: areturn

  public default void setBlock(int, int, int, java.lang.String);
    Code:
         0: aload_0
         1: iload_1
         2: iload_2
         3: iload_3
         4: aload         4
         6: iconst_0
         7: invokeinterface #50,  6           // InterfaceMethod setBlock:(IIILjava/lang/String;I)V
        12: return

  public default void setBlock(int, int, int, java.lang.String, int);
    Code:
         0: aload_0
         1: iload_1
         2: iload_3
         3: invokestatic  #19                 // Method com/hypixel/hytale/math/util/ChunkUtil.indexChunkFromBlock:(II)J
         6: invokeinterface #25,  3           // InterfaceMethod getChunk:(J)Lcom/hypixel/hytale/server/core/universe/world/accessor/BlockAccessor;
        11: iload_1
        12: iload_2
        13: iload_3
        14: aload         4
        16: iload         5
        18: invokeinterface #54,  6           // InterfaceMethod com/hypixel/hytale/server/core/universe/world/accessor/BlockAccessor.setBlock:(IIILjava/lang/String;I)Z
        23: pop
        24: return

  public default boolean breakBlock(int, int, int, int);
    Code:
         0: aload_0
         1: iload_1
         2: iload_3
         3: invokestatic  #19                 // Method com/hypixel/hytale/math/util/ChunkUtil.indexChunkFromBlock:(II)J
         6: invokeinterface #25,  3           // InterfaceMethod getChunk:(J)Lcom/hypixel/hytale/server/core/universe/world/accessor/BlockAccessor;
        11: iload_1
        12: iload_2
        13: iload_3
        14: iload         4
        16: invokeinterface #57,  5           // InterfaceMethod com/hypixel/hytale/server/core/universe/world/accessor/BlockAccessor.breakBlock:(IIII)Z
        21: ireturn

  public default boolean testBlockTypes(int, int, int, com.hypixel.hytale.server.core.asset.type.blocktype.config.BlockType, int, com.hypixel.hytale.server.core.universe.world.accessor.IChunkAccessorSync$TestBlockFunction);
    Code:
         0: aload_0
         1: iload_1
         2: iload_3
         3: invokestatic  #19                 // Method com/hypixel/hytale/math/util/ChunkUtil.indexChunkFromBlock:(II)J
         6: invokeinterface #25,  3           // InterfaceMethod getChunk:(J)Lcom/hypixel/hytale/server/core/universe/world/accessor/BlockAccessor;
        11: iload_1
        12: iload_2
        13: iload_3
        14: aload         4
        16: iload         5
        18: aload         6
        20: invokeinterface #61,  7           // InterfaceMethod com/hypixel/hytale/server/core/universe/world/accessor/BlockAccessor.testBlockTypes:(IIILcom/hypixel/hytale/server/core/asset/type/blocktype/config/BlockType;ILcom/hypixel/hytale/server/core/universe/world/accessor/IChunkAccessorSync$TestBlockFunction;)Z
        25: ireturn

  public default boolean testPlaceBlock(int, int, int, com.hypixel.hytale.server.core.asset.type.blocktype.config.BlockType, int);
    Code:
         0: aload_0
         1: iload_1
         2: iload_3
         3: invokestatic  #19                 // Method com/hypixel/hytale/math/util/ChunkUtil.indexChunkFromBlock:(II)J
         6: invokeinterface #25,  3           // InterfaceMethod getChunk:(J)Lcom/hypixel/hytale/server/core/universe/world/accessor/BlockAccessor;
        11: iload_1
        12: iload_2
        13: iload_3
        14: aload         4
        16: iload         5
        18: invokeinterface #65,  6           // InterfaceMethod com/hypixel/hytale/server/core/universe/world/accessor/BlockAccessor.testPlaceBlock:(IIILcom/hypixel/hytale/server/core/asset/type/blocktype/config/BlockType;I)Z
        23: ireturn

  public default boolean testPlaceBlock(int, int, int, com.hypixel.hytale.server.core.asset.type.blocktype.config.BlockType, int, com.hypixel.hytale.server.core.universe.world.accessor.IChunkAccessorSync$TestBlockFunction);
    Code:
         0: aload_0
         1: iload_1
         2: iload_3
         3: invokestatic  #19                 // Method com/hypixel/hytale/math/util/ChunkUtil.indexChunkFromBlock:(II)J
         6: invokeinterface #25,  3           // InterfaceMethod getChunk:(J)Lcom/hypixel/hytale/server/core/universe/world/accessor/BlockAccessor;
        11: iload_1
        12: iload_2
        13: iload_3
        14: aload         4
        16: iload         5
        18: aload         6
        20: invokeinterface #69,  7           // InterfaceMethod com/hypixel/hytale/server/core/universe/world/accessor/BlockAccessor.testPlaceBlock:(IIILcom/hypixel/hytale/server/core/asset/type/blocktype/config/BlockType;ILcom/hypixel/hytale/server/core/universe/world/accessor/IChunkAccessorSync$TestBlockFunction;)Z
        25: ireturn

  public default com.hypixel.hytale.component.Holder<com.hypixel.hytale.server.core.universe.world.storage.ChunkStore> getBlockComponentHolder(int, int, int);
    Code:
         0: iload_2
         1: iflt          11
         4: iload_2
         5: sipush        320
         8: if_icmplt     13
        11: aconst_null
        12: areturn
        13: aload_0
        14: iload_1
        15: iload_3
        16: invokestatic  #19                 // Method com/hypixel/hytale/math/util/ChunkUtil.indexChunkFromBlock:(II)J
        19: invokeinterface #25,  3           // InterfaceMethod getChunk:(J)Lcom/hypixel/hytale/server/core/universe/world/accessor/BlockAccessor;
        24: iload_1
        25: iload_2
        26: iload_3
        27: invokeinterface #71,  4           // InterfaceMethod com/hypixel/hytale/server/core/universe/world/accessor/BlockAccessor.getBlockComponentHolder:(III)Lcom/hypixel/hytale/component/Holder;
        32: areturn

  public default void setBlockInteractionState(org.joml.Vector3i, com.hypixel.hytale.server.core.asset.type.blocktype.config.BlockType, java.lang.String);
    Code:
         0: aload_0
         1: aload_1
         2: getfield      #75                 // Field org/joml/Vector3i.x:I
         5: aload_1
         6: getfield      #78                 // Field org/joml/Vector3i.z:I
         9: invokestatic  #19                 // Method com/hypixel/hytale/math/util/ChunkUtil.indexChunkFromBlock:(II)J
        12: invokeinterface #25,  3           // InterfaceMethod getChunk:(J)Lcom/hypixel/hytale/server/core/universe/world/accessor/BlockAccessor;
        17: aload_1
        18: aload_2
        19: aload_3
        20: invokeinterface #80,  4           // InterfaceMethod com/hypixel/hytale/server/core/universe/world/accessor/BlockAccessor.setBlockInteractionState:(Lorg/joml/Vector3i;Lcom/hypixel/hytale/server/core/asset/type/blocktype/config/BlockType;Ljava/lang/String;)V
        25: return

  public default com.hypixel.hytale.protocol.BlockPosition getBaseBlock(com.hypixel.hytale.protocol.BlockPosition);
    Code:
         0: aload_0
         1: aload_1
         2: getfield      #84                 // Field com/hypixel/hytale/protocol/BlockPosition.x:I
         5: aload_1
         6: getfield      #87                 // Field com/hypixel/hytale/protocol/BlockPosition.z:I
         9: invokestatic  #19                 // Method com/hypixel/hytale/math/util/ChunkUtil.indexChunkFromBlock:(II)J
        12: invokeinterface #88,  3           // InterfaceMethod getNonTickingChunk:(J)Lcom/hypixel/hytale/server/core/universe/world/accessor/BlockAccessor;
        17: astore_2
        18: aload_2
        19: aload_1
        20: getfield      #84                 // Field com/hypixel/hytale/protocol/BlockPosition.x:I
        23: aload_1
        24: getfield      #91                 // Field com/hypixel/hytale/protocol/BlockPosition.y:I
        27: aload_1
        28: getfield      #87                 // Field com/hypixel/hytale/protocol/BlockPosition.z:I
        31: invokeinterface #93,  4           // InterfaceMethod com/hypixel/hytale/server/core/universe/world/accessor/BlockAccessor.getFiller:(III)I
        36: istore_3
        37: iload_3
        38: ifeq          76
        41: new           #85                 // class com/hypixel/hytale/protocol/BlockPosition
        44: dup
        45: aload_1
        46: getfield      #84                 // Field com/hypixel/hytale/protocol/BlockPosition.x:I
        49: iload_3
        50: invokestatic  #96                 // Method com/hypixel/hytale/server/core/util/FillerBlockUtil.unpackX:(I)I
        53: isub
        54: aload_1
        55: getfield      #91                 // Field com/hypixel/hytale/protocol/BlockPosition.y:I
        58: iload_3
        59: invokestatic  #102                // Method com/hypixel/hytale/server/core/util/FillerBlockUtil.unpackY:(I)I
        62: isub
        63: aload_1
        64: getfield      #87                 // Field com/hypixel/hytale/protocol/BlockPosition.z:I
        67: iload_3
        68: invokestatic  #105                // Method com/hypixel/hytale/server/core/util/FillerBlockUtil.unpackZ:(I)I
        71: isub
        72: invokespecial #108                // Method com/hypixel/hytale/protocol/BlockPosition."<init>":(III)V
        75: areturn
        76: aload_1
        77: areturn

  public default int getBlockRotationIndex(int, int, int);
    Code:
         0: aload_0
         1: iload_1
         2: iload_3
         3: invokestatic  #19                 // Method com/hypixel/hytale/math/util/ChunkUtil.indexChunkFromBlock:(II)J
         6: invokeinterface #25,  3           // InterfaceMethod getChunk:(J)Lcom/hypixel/hytale/server/core/universe/world/accessor/BlockAccessor;
        11: iload_1
        12: iload_2
        13: iload_3
        14: invokeinterface #112,  4          // InterfaceMethod com/hypixel/hytale/server/core/universe/world/accessor/BlockAccessor.getRotationIndex:(III)I
        19: ireturn
}
